distribute_setup.py
setup.py
webveripy/__init__.py
webveripy/webtest.py
webveripy.egg-info/PKG-INFO
webveripy.egg-info/SOURCES.txt
webveripy.egg-info/dependency_links.txt
webveripy.egg-info/requires.txt
webveripy.egg-info/top_level.txt