Metadata-Version: 1.0
Name: webveripy
Version: 0.3
Summary: All-purpose web verification framework.
Home-page: https://github.com/jharen/Webveripy
Author: john haren
Author-email: john.haren@gmail.com
License: UNKNOWN
Platform: UNKNOWN
